fmu_settings_cli/__init__.py
fmu_settings_cli/__main__.py
fmu_settings_cli/_version.py
fmu_settings_cli/prints.py
fmu_settings_cli/py.typed
fmu_settings_cli/types.py
fmu_settings_cli/init/__init__.py
fmu_settings_cli/init/cli.py
fmu_settings_cli/settings/__init__.py
fmu_settings_cli/settings/_utils.py
fmu_settings_cli/settings/api_server.py
fmu_settings_cli/settings/cli.py
fmu_settings_cli/settings/constants.py
fmu_settings_cli/settings/gui_server.py
fmu_settings_cli/settings/main.py
fmu_settings_cli/sync/__init__.py
fmu_settings_cli/sync/cli.py
fmu_settings_cli/sync/model_diff.py
fmu_settings_cli-0.1.1.dist-info/licenses/LICENSE
fmu_settings_cli-0.1.1.dist-info/METADATA
fmu_settings_cli-0.1.1.dist-info/WHEEL
fmu_settings_cli-0.1.1.dist-info/entry_points.txt
fmu_settings_cli-0.1.1.dist-info/top_level.txt
fmu_settings_cli-0.1.1.dist-info/RECORD
