Metadata-Version: 2.4
Name: fmu-settings-cli
Version: 0.1.1
Summary: The cli for fmu-settings
Author-email: Equinor <fg-fmu_atlas@equinor.com>
License: GPL-3.0
Project-URL: Homepage, https://github.com/equinor/fmu-settings-cli
Project-URL: Repository, https://github.com/equinor/fmu-settings-cli
Project-URL: Documentation, https://github.com/equinor/fmu-settings-cli
Classifier: Development Status :: 3 - Alpha
Classifier: Topic :: Scientific/Engineering
Classifier: Topic :: Utilities
Classifier: Operating System :: POSIX :: Linux
Classifier: Programming Language :: Python :: 3.11
Classifier: Programming Language :: Python :: 3.12
Classifier: Natural Language :: English
Requires-Python: >=3.11
License-File: LICENSE
Requires-Dist: fmu-datamodels
Requires-Dist: fmu-settings
Requires-Dist: fmu-settings-api
Requires-Dist: fmu-settings-gui
Requires-Dist: rich
Requires-Dist: typer
Provides-Extra: dev
Requires-Dist: mypy; extra == "dev"
Requires-Dist: pytest; extra == "dev"
Requires-Dist: pytest-cov; extra == "dev"
Requires-Dist: pytest-mock; extra == "dev"
Requires-Dist: pytest-xdist; extra == "dev"
Requires-Dist: ruff; extra == "dev"
Requires-Dist: PyYAML; extra == "dev"
Requires-Dist: types-PyYAML; extra == "dev"
Dynamic: license-file
